m5tlproftomegz/__init__.py
m5tlprovetomegz-0.1.1.dist-info/METADATA
m5tlprovetomegz-0.1.1.dist-info/WHEEL
m5tlprovetomegz-0.1.1.dist-info/top_level.txt
m5tlprovetomegz-0.1.1.dist-info/RECORD
