Metadata-Version: 2.4
Name: m5tlprovetomegz
Version: 0.1.1
Summary: وصف قصير للمكتبة
Author: m5tl
Classifier: Programming Language :: Python :: 3
Classifier: Operating System :: OS Independent
Requires-Python: >=3.6
Dynamic: author
Dynamic: classifier
Dynamic: description
Dynamic: description-content-type
Dynamic: requires-python
Dynamic: summary
